MANIFEST.in
README.txt
cfgparse.py
release_instructions.txt
setup.py
cfgparse.egg-info/PKG-INFO
cfgparse.egg-info/SOURCES.txt
cfgparse.egg-info/dependency_links.txt
cfgparse.egg-info/top_level.txt
docs/cfgparse.pdf
docs/cfgparse.tex
tests/cfgparse_py_doctest.py
tests/cfgparse_tex_doctest.py
