Metadata-Version: 1.0
Name: cfgparse
Version: 1.3
Summary: Configuration Parser Module
Home-page: https://sourceforge.net/projects/cfgparse/
Author: Daniel M. Gass
Author-email: dan.gass@gmail.com
License: UNKNOWN
Platform: UNKNOWN
